{
  "fill" : {
    "solid" : "srgb:1.00000,0.85490,0.37647,1.00000"
  },
  "groups" : [
    {
      "layers" : [
        {
          "fill-specializations" : [
            {
              "appearance" : "tinted",
              "value" : {
                "solid" : "gray:0.20499,1.00000"
              }
            }
          ],
          "glass" : false,
          "image-name" : "notes-squiggle.svg",
          "name" : "notes-squiggle"
        },
        {
          "fill-specializations" : [
            {
              "appearance" : "tinted",
              "value" : {
                "linear-gradient" : [
                  "gray:0.79767,1.00000",
                  "gray:0.64866,1.00000"
                ]
              }
            }
          ],
          "hidden" : false,
          "image-name" : "notes-top.svg",
          "name" : "notes-top"
        },
        {
          "blend-mode-specializations" : [
            {
              "value" : "normal"
            },
            {
              "appearance" : "dark",
              "value" : "normal"
            },
            {
              "appearance" : "tinted",
              "value" : "normal"
            }
          ],
          "fill-specializations" : [
            {
              "value" : {
                "solid" : "srgb:1.00000,1.00000,1.00000,1.00000"
              }
            },
            {
              "appearance" : "dark",
              "value" : {
                "solid" : "srgb:0.93333,0.83922,0.45098,1.00000"
              }
            },
            {
              "appearance" : "tinted",
              "value" : {
                "solid" : "gray:0.94624,1.00000"
              }
            }
          ],
          "hidden" : false,
          "image-name" : "notes-bottom.svg",
          "name" : "notes-bottom",
          "opacity-specializations" : [
            {
              "value" : 0.8
            },
            {
              "appearance" : "dark",
              "value" : 0.6
            },
            {
              "appearance" : "tinted",
              "value" : 0.8
            }
          ]
        },
        {
          "fill-specializations" : [
            {
              "appearance" : "tinted",
              "value" : {
                "solid" : "gray:0.29895,1.00000"
              }
            }
          ],
          "image-name" : "notes-middle.svg",
          "name" : "notes-middle"
        },
        {
          "blend-mode-specializations" : [
            {
              "value" : "normal"
            },
            {
              "appearance" : "dark",
              "value" : "normal"
            },
            {
              "appearance" : "tinted",
              "value" : "normal"
            }
          ],
          "fill-specializations" : [
            {
              "value" : {
                "solid" : "srgb:1.00000,1.00000,1.00000,1.00000"
              }
            },
            {
              "appearance" : "dark",
              "value" : {
                "solid" : "srgb:0.93333,0.83922,0.45098,1.00000"
              }
            },
            {
              "appearance" : "tinted",
              "value" : {
                "solid" : "gray:0.94624,1.00000"
              }
            }
          ],
          "glass" : false,
          "hidden" : false,
          "image-name" : "notes-bottom.svg",
          "name" : "notes-bottom",
          "opacity-specializations" : [
            {
              "value" : 0.9
            },
            {
              "appearance" : "tinted",
              "value" : 0.9
            }
          ]
        }
      ],
      "shadow" : {
        "kind" : "neutral",
        "opacity" : 0.5
      },
      "translucency" : {
        "enabled" : false,
        "value" : 0.2
      }
    }
  ],
  "supported-platforms" : {
    "squares" : [
      "iOS"
    ]
  }
}
